fastrand.cpython-311-darwin.so
fastrand-3.0.7.dist-info/licenses/LICENSE
fastrand-3.0.7.dist-info/METADATA
fastrand-3.0.7.dist-info/WHEEL
fastrand-3.0.7.dist-info/top_level.txt
fastrand-3.0.7.dist-info/RECORD
