Metadata-Version: 2.1
Name: fastrand
Version: 3.0.7
Summary: Fast random number generation in Python
Author-email: Daniel Lemire <daniel@lemire.me>
License: Apache-2.0
Project-URL: Homepage, https://github.com/lemire/fastrand
Project-URL: Repository, https://github.com/lemire/fastrand
Project-URL: Issues, https://github.com/lemire/fastrand/issues
Keywords: random,random-number-generator,pcg,xorshift,performance
Classifier: Development Status :: 5 - Production/Stable
Classifier: Intended Audience :: Developers
Classifier: Intended Audience :: Science/Research
Classifier: Programming Language :: C
Classifier: Programming Language :: Python :: 3
Classifier: Programming Language :: Python :: 3.8
Classifier: Programming Language :: Python :: 3.9
Classifier: Programming Language :: Python :: 3.10
Classifier: Programming Language :: Python :: 3.11
Classifier: Programming Language :: Python :: 3.12
Classifier: Programming Language :: Python :: 3.13
Classifier: Topic :: Scientific/Engineering
Classifier: Topic :: Software Development :: Libraries
Requires-Python: >=3.8
License-File: LICENSE
